{"box_data": [{"position": {"minX": 221.75, "minY": 17.125, "maxX": 322.25, "maxY": 131.5}, "class_id": 0, "box_caption": "bone-loss 0.644", "scores": {"class_score": 0.6435546875}, "domain": "pixel"}, {"position": {"minX": 221.75, "minY": 17.125, "maxX": 322.25, "maxY": 131.5}, "class_id": 1, "box_caption": "dental-caries 0.641", "scores": {"class_score": 0.64111328125}, "domain": "pixel"}, {"position": {"minX": 253.875, "minY": 87.125, "maxX": 356.75, "maxY": 203.375}, "class_id": 0, "box_caption": "bone-loss 0.625", "scores": {"class_score": 0.625}, "domain": "pixel"}, {"position": {"minX": 253.875, "minY": 87.125, "maxX": 356.75, "maxY": 203.375}, "class_id": 1, "box_caption": "dental-caries 0.622", "scores": {"class_score": 0.6220703125}, "domain": "pixel"}, {"position": {"minX": 284.25, "minY": 13.34375, "maxX": 387.25, "maxY": 132.625}, "class_id": 0, "box_caption": "bone-loss 0.580", "scores": {"class_score": 0.57958984375}, "domain": "pixel"}, {"position": {"minX": 284.25, "minY": 13.34375, "maxX": 387.25, "maxY": 132.625}, "class_id": 1, "box_caption": "dental-caries 0.575", "scores": {"class_score": 0.57470703125}, "domain": "pixel"}, {"position": {"minX": 283.0, "minY": 59.75, "maxX": 387.0, "maxY": 176.0}, "class_id": 0, "box_caption": "bone-loss 0.541", "scores": {"class_score": 0.541015625}, "domain": "pixel"}, {"position": {"minX": 283.0, "minY": 59.75, "maxX": 387.0, "maxY": 176.0}, "class_id": 1, "box_caption": "dental-caries 0.541", "scores": {"class_score": 0.54052734375}, "domain": "pixel"}, {"position": {"minX": 220.625, "minY": 121.875, "maxX": 322.0, "maxY": 238.625}, "class_id": 0, "box_caption": "bone-loss 0.481", "scores": {"class_score": 0.48095703125}, "domain": "pixel"}, {"position": {"minX": 220.625, "minY": 121.875, "maxX": 322.0, "maxY": 238.625}, "class_id": 1, "box_caption": "dental-caries 0.481", "scores": {"class_score": 0.480712890625}, "domain": "pixel"}, {"position": {"minX": 223.0, "minY": 185.25, "maxX": 319.5, "maxY": 299.25}, "class_id": 0, "box_caption": "bone-loss 0.449", "scores": {"class_score": 0.448974609375}, "domain": "pixel"}, {"position": {"minX": 14.375, "minY": 11.65625, "maxX": 133.375, "maxY": 138.625}, "class_id": 0, "box_caption": "bone-loss 0.448", "scores": {"class_score": 0.448486328125}, "domain": "pixel"}, {"position": {"minX": 223.0, "minY": 185.25, "maxX": 319.5, "maxY": 299.25}, "class_id": 1, "box_caption": "dental-caries 0.447", "scores": {"class_score": 0.44677734375}, "domain": "pixel"}, {"position": {"minX": 14.375, "minY": 11.65625, "maxX": 133.375, "maxY": 138.625}, "class_id": 1, "box_caption": "dental-caries 0.446", "scores": {"class_score": 0.4462890625}, "domain": "pixel"}, {"position": {"minX": 282.75, "minY": 121.5, "maxX": 386.75, "maxY": 237.0}, "class_id": 0, "box_caption": "bone-loss 0.445", "scores": {"class_score": 0.444580078125}, "domain": "pixel"}, {"position": {"minX": 282.75, "minY": 121.5, "maxX": 386.75, "maxY": 237.0}, "class_id": 1, "box_caption": "dental-caries 0.444", "scores": {"class_score": 0.44384765625}, "domain": "pixel"}, {"position": {"minX": 187.5, "minY": 82.4375, "maxX": 293.5, "maxY": 204.0}, "class_id": 0, "box_caption": "bone-loss 0.431", "scores": {"class_score": 0.4306640625}, "domain": "pixel"}, {"position": {"minX": 187.5, "minY": 82.4375, "maxX": 293.5, "maxY": 204.0}, "class_id": 1, "box_caption": "dental-caries 0.430", "scores": {"class_score": 0.43017578125}, "domain": "pixel"}, {"position": {"minX": 90.75, "minY": 13.5625, "maxX": 201.0, "maxY": 135.5}, "class_id": 0, "box_caption": "bone-loss 0.427", "scores": {"class_score": 0.427490234375}, "domain": "pixel"}, {"position": {"minX": 255.625, "minY": 155.625, "maxX": 354.0, "maxY": 260.25}, "class_id": 0, "box_caption": "bone-loss 0.427", "scores": {"class_score": 0.427001953125}, "domain": "pixel"}, {"position": {"minX": 255.625, "minY": 155.625, "maxX": 354.0, "maxY": 260.25}, "class_id": 1, "box_caption": "dental-caries 0.425", "scores": {"class_score": 0.424560546875}, "domain": "pixel"}, {"position": {"minX": 90.75, "minY": 13.5625, "maxX": 201.0, "maxY": 135.5}, "class_id": 1, "box_caption": "dental-caries 0.423", "scores": {"class_score": 0.4228515625}, "domain": "pixel"}, {"position": {"minX": 348.25, "minY": 83.375, "maxX": 451.25, "maxY": 205.625}, "class_id": 0, "box_caption": "bone-loss 0.414", "scores": {"class_score": 0.41357421875}, "domain": "pixel"}, {"position": {"minX": 348.25, "minY": 83.375, "maxX": 451.25, "maxY": 205.625}, "class_id": 1, "box_caption": "dental-caries 0.412", "scores": {"class_score": 0.412109375}, "domain": "pixel"}, {"position": {"minX": 158.5, "minY": 10.9375, "maxX": 260.0, "maxY": 137.0}, "class_id": 0, "box_caption": "bone-loss 0.408", "scores": {"class_score": 0.408203125}, "domain": "pixel"}, {"position": {"minX": 158.5, "minY": 10.9375, "maxX": 260.0, "maxY": 137.0}, "class_id": 1, "box_caption": "dental-caries 0.406", "scores": {"class_score": 0.406494140625}, "domain": "pixel"}, {"position": {"minX": 287.75, "minY": 185.625, "maxX": 383.25, "maxY": 295.25}, "class_id": 0, "box_caption": "bone-loss 0.397", "scores": {"class_score": 0.396728515625}, "domain": "pixel"}, {"position": {"minX": 287.75, "minY": 185.625, "maxX": 383.25, "maxY": 295.25}, "class_id": 1, "box_caption": "dental-caries 0.393", "scores": {"class_score": 0.393310546875}, "domain": "pixel"}, {"position": {"minX": 253.0, "minY": -6.8125, "maxX": 358.0, "maxY": 104.0}, "class_id": 0, "box_caption": "bone-loss 0.389", "scores": {"class_score": 0.38916015625}, "domain": "pixel"}, {"position": {"minX": 354.75, "minY": 181.125, "maxX": 443.75, "maxY": 298.0}, "class_id": 1, "box_caption": "dental-caries 0.389", "scores": {"class_score": 0.388671875}, "domain": "pixel"}, {"position": {"minX": 253.0, "minY": -6.8125, "maxX": 358.0, "maxY": 104.0}, "class_id": 1, "box_caption": "dental-caries 0.389", "scores": {"class_score": 0.388671875}, "domain": "pixel"}, {"position": {"minX": 354.75, "minY": 181.125, "maxX": 443.75, "maxY": 298.0}, "class_id": 0, "box_caption": "bone-loss 0.388", "scores": {"class_score": 0.388427734375}, "domain": "pixel"}, {"position": {"minX": 258.5, "minY": 212.75, "maxX": 350.5, "maxY": 322.25}, "class_id": 0, "box_caption": "bone-loss 0.342", "scores": {"class_score": 0.341796875}, "domain": "pixel"}, {"position": {"minX": 258.5, "minY": 212.75, "maxX": 350.5, "maxY": 322.25}, "class_id": 1, "box_caption": "dental-caries 0.340", "scores": {"class_score": 0.34033203125}, "domain": "pixel"}, {"position": {"minX": 185.0, "minY": -6.875, "maxX": 291.5, "maxY": 102.25}, "class_id": 1, "box_caption": "dental-caries 0.325", "scores": {"class_score": 0.324951171875}, "domain": "pixel"}, {"position": {"minX": 185.0, "minY": -6.875, "maxX": 291.5, "maxY": 102.25}, "class_id": 0, "box_caption": "bone-loss 0.323", "scores": {"class_score": 0.32275390625}, "domain": "pixel"}, {"position": {"minX": 224.5, "minY": 255.0, "maxX": 317.0, "maxY": 356.5}, "class_id": 1, "box_caption": "dental-caries 0.309", "scores": {"class_score": 0.30859375}, "domain": "pixel"}, {"position": {"minX": 224.5, "minY": 255.0, "maxX": 317.0, "maxY": 356.5}, "class_id": 0, "box_caption": "bone-loss 0.308", "scores": {"class_score": 0.30810546875}, "domain": "pixel"}, {"position": {"minX": 64.75, "minY": -11.84375, "maxX": 180.5, "maxY": 106.125}, "class_id": 0, "box_caption": "bone-loss 0.285", "scores": {"class_score": 0.285400390625}, "domain": "pixel"}, {"position": {"minX": 346.75, "minY": 7.5625, "maxX": 453.25, "maxY": 135.5}, "class_id": 0, "box_caption": "bone-loss 0.284", "scores": {"class_score": 0.284423828125}, "domain": "pixel"}, {"position": {"minX": 126.75, "minY": -9.5, "maxX": 235.0, "maxY": 104.5}, "class_id": 0, "box_caption": "bone-loss 0.284", "scores": {"class_score": 0.2841796875}, "domain": "pixel"}, {"position": {"minX": 126.75, "minY": -9.5, "maxX": 235.0, "maxY": 104.5}, "class_id": 1, "box_caption": "dental-caries 0.283", "scores": {"class_score": 0.282958984375}, "domain": "pixel"}, {"position": {"minX": 346.75, "minY": 7.5625, "maxX": 453.25, "maxY": 135.5}, "class_id": 1, "box_caption": "dental-caries 0.283", "scores": {"class_score": 0.28271484375}, "domain": "pixel"}, {"position": {"minX": 64.75, "minY": -11.84375, "maxX": 180.5, "maxY": 106.125}, "class_id": 1, "box_caption": "dental-caries 0.280", "scores": {"class_score": 0.280029296875}, "domain": "pixel"}, {"position": {"minX": 260.25, "minY": 278.5, "maxX": 350.75, "maxY": 393.5}, "class_id": 0, "box_caption": "bone-loss 0.271", "scores": {"class_score": 0.271240234375}, "domain": "pixel"}, {"position": {"minX": 57.25, "minY": 52.625, "maxX": 180.0, "maxY": 181.375}, "class_id": 0, "box_caption": "bone-loss 0.270", "scores": {"class_score": 0.269775390625}, "domain": "pixel"}, {"position": {"minX": 260.25, "minY": 278.5, "maxX": 350.75, "maxY": 393.5}, "class_id": 1, "box_caption": "dental-caries 0.270", "scores": {"class_score": 0.26953125}, "domain": "pixel"}, {"position": {"minX": 57.25, "minY": 52.625, "maxX": 180.0, "maxY": 181.375}, "class_id": 1, "box_caption": "dental-caries 0.264", "scores": {"class_score": 0.264404296875}, "domain": "pixel"}, {"position": {"minX": -9.625, "minY": 48.5625, "maxX": 103.5625, "maxY": 195.75}, "class_id": 0, "box_caption": "bone-loss 0.231", "scores": {"class_score": 0.231201171875}, "domain": "pixel"}, {"position": {"minX": 218.125, "minY": -41.09375, "maxX": 327.0, "maxY": 74.0}, "class_id": 0, "box_caption": "bone-loss 0.231", "scores": {"class_score": 0.2310791015625}, "domain": "pixel"}, {"position": {"minX": 218.125, "minY": -41.09375, "maxX": 327.0, "maxY": 74.0}, "class_id": 1, "box_caption": "dental-caries 0.230", "scores": {"class_score": 0.229736328125}, "domain": "pixel"}, {"position": {"minX": 186.125, "minY": 152.875, "maxX": 294.0, "maxY": 263.0}, "class_id": 1, "box_caption": "dental-caries 0.227", "scores": {"class_score": 0.226806640625}, "domain": "pixel"}, {"position": {"minX": 186.125, "minY": 152.875, "maxX": 294.0, "maxY": 263.0}, "class_id": 0, "box_caption": "bone-loss 0.225", "scores": {"class_score": 0.2249755859375}, "domain": "pixel"}, {"position": {"minX": -9.625, "minY": 48.5625, "maxX": 103.5625, "maxY": 195.75}, "class_id": 1, "box_caption": "dental-caries 0.224", "scores": {"class_score": 0.223876953125}, "domain": "pixel"}, {"position": {"minX": 291.5, "minY": 252.875, "maxX": 381.5, "maxY": 358.5}, "class_id": 0, "box_caption": "bone-loss 0.224", "scores": {"class_score": 0.2237548828125}, "domain": "pixel"}, {"position": {"minX": 291.5, "minY": 252.875, "maxX": 381.5, "maxY": 358.5}, "class_id": 1, "box_caption": "dental-caries 0.223", "scores": {"class_score": 0.223388671875}, "domain": "pixel"}, {"position": {"minX": 312.0, "minY": -9.90625, "maxX": 421.5, "maxY": 110.625}, "class_id": 1, "box_caption": "dental-caries 0.220", "scores": {"class_score": 0.22021484375}, "domain": "pixel"}, {"position": {"minX": 312.0, "minY": -9.90625, "maxX": 421.5, "maxY": 110.625}, "class_id": 0, "box_caption": "bone-loss 0.219", "scores": {"class_score": 0.219482421875}, "domain": "pixel"}, {"position": {"minX": 120.375, "minY": 53.375, "maxX": 236.625, "maxY": 182.5}, "class_id": 0, "box_caption": "bone-loss 0.209", "scores": {"class_score": 0.2091064453125}, "domain": "pixel"}, {"position": {"minX": 120.375, "minY": 53.375, "maxX": 236.625, "maxY": 182.5}, "class_id": 1, "box_caption": "dental-caries 0.207", "scores": {"class_score": 0.2066650390625}, "domain": "pixel"}, {"position": {"minX": 320.75, "minY": 153.75, "maxX": 414.25, "maxY": 263.25}, "class_id": 1, "box_caption": "dental-caries 0.203", "scores": {"class_score": 0.202880859375}, "domain": "pixel"}, {"position": {"minX": 320.75, "minY": 153.75, "maxX": 414.25, "maxY": 263.25}, "class_id": 0, "box_caption": "bone-loss 0.202", "scores": {"class_score": 0.2022705078125}, "domain": "pixel"}, {"position": {"minX": 223.75, "minY": 310.25, "maxX": 317.25, "maxY": 419.75}, "class_id": 1, "box_caption": "dental-caries 0.201", "scores": {"class_score": 0.2012939453125}, "domain": "pixel"}, {"position": {"minX": 223.75, "minY": 310.25, "maxX": 317.25, "maxY": 419.75}, "class_id": 0, "box_caption": "bone-loss 0.201", "scores": {"class_score": 0.2005615234375}, "domain": "pixel"}, {"position": {"minX": 191.0, "minY": 279.75, "maxX": 288.5, "maxY": 392.75}, "class_id": 0, "box_caption": "bone-loss 0.182", "scores": {"class_score": 0.181640625}, "domain": "pixel"}, {"position": {"minX": 191.0, "minY": 279.75, "maxX": 288.5, "maxY": 392.75}, "class_id": 1, "box_caption": "dental-caries 0.181", "scores": {"class_score": 0.1812744140625}, "domain": "pixel"}, {"position": {"minX": 220.875, "minY": 348.0, "maxX": 319.75, "maxY": 466.5}, "class_id": 0, "box_caption": "bone-loss 0.175", "scores": {"class_score": 0.175048828125}, "domain": "pixel"}, {"position": {"minX": 220.875, "minY": 348.0, "maxX": 319.75, "maxY": 466.5}, "class_id": 1, "box_caption": "dental-caries 0.175", "scores": {"class_score": 0.1748046875}, "domain": "pixel"}, {"position": {"minX": 155.875, "minY": -42.46875, "maxX": 263.0, "maxY": 74.875}, "class_id": 0, "box_caption": "bone-loss 0.172", "scores": {"class_score": 0.1724853515625}, "domain": "pixel"}, {"position": {"minX": 155.875, "minY": -42.46875, "maxX": 263.0, "maxY": 74.875}, "class_id": 1, "box_caption": "dental-caries 0.172", "scores": {"class_score": 0.17236328125}, "domain": "pixel"}, {"position": {"minX": 190.375, "minY": 215.375, "maxX": 290.0, "maxY": 322.75}, "class_id": 1, "box_caption": "dental-caries 0.165", "scores": {"class_score": 0.1654052734375}, "domain": "pixel"}, {"position": {"minX": 190.375, "minY": 215.375, "maxX": 290.0, "maxY": 322.75}, "class_id": 0, "box_caption": "bone-loss 0.163", "scores": {"class_score": 0.1629638671875}, "domain": "pixel"}, {"position": {"minX": 9.03125, "minY": -42.4375, "maxX": 136.25, "maxY": 74.8125}, "class_id": 0, "box_caption": "bone-loss 0.157", "scores": {"class_score": 0.1571044921875}, "domain": "pixel"}, {"position": {"minX": 9.03125, "minY": -42.4375, "maxX": 136.25, "maxY": 74.8125}, "class_id": 1, "box_caption": "dental-caries 0.157", "scores": {"class_score": 0.1566162109375}, "domain": "pixel"}, {"position": {"minX": -34.84375, "minY": 9.4375, "maxX": 67.0, "maxY": 135.5}, "class_id": 0, "box_caption": "bone-loss 0.155", "scores": {"class_score": 0.155029296875}, "domain": "pixel"}, {"position": {"minX": 88.3125, "minY": -42.53125, "maxX": 204.75, "maxY": 76.25}, "class_id": 0, "box_caption": "bone-loss 0.154", "scores": {"class_score": 0.15380859375}, "domain": "pixel"}, {"position": {"minX": 279.0, "minY": -44.125, "maxX": 392.0, "maxY": 73.8125}, "class_id": 1, "box_caption": "dental-caries 0.153", "scores": {"class_score": 0.1533203125}, "domain": "pixel"}, {"position": {"minX": 279.0, "minY": -44.125, "maxX": 392.0, "maxY": 73.8125}, "class_id": 0, "box_caption": "bone-loss 0.153", "scores": {"class_score": 0.1527099609375}, "domain": "pixel"}, {"position": {"minX": -34.84375, "minY": 9.4375, "maxX": 67.0, "maxY": 135.5}, "class_id": 1, "box_caption": "dental-caries 0.151", "scores": {"class_score": 0.1510009765625}, "domain": "pixel"}, {"position": {"minX": 88.3125, "minY": -42.53125, "maxX": 204.75, "maxY": 76.25}, "class_id": 1, "box_caption": "dental-caries 0.150", "scores": {"class_score": 0.150390625}, "domain": "pixel"}, {"position": {"minX": -8.21875, "minY": -13.9375, "maxX": 101.375, "maxY": 108.6875}, "class_id": 0, "box_caption": "bone-loss 0.144", "scores": {"class_score": 0.1444091796875}, "domain": "pixel"}, {"position": {"minX": -8.21875, "minY": -13.9375, "maxX": 101.375, "maxY": 108.6875}, "class_id": 1, "box_caption": "dental-caries 0.143", "scores": {"class_score": 0.14306640625}, "domain": "pixel"}, {"position": {"minX": 252.625, "minY": 366.5, "maxX": 358.5, "maxY": 489.5}, "class_id": 0, "box_caption": "bone-loss 0.141", "scores": {"class_score": 0.1407470703125}, "domain": "pixel"}, {"position": {"minX": 252.625, "minY": 366.5, "maxX": 358.5, "maxY": 489.5}, "class_id": 1, "box_caption": "dental-caries 0.141", "scores": {"class_score": 0.1405029296875}, "domain": "pixel"}, {"position": {"minX": 323.0, "minY": 209.375, "maxX": 411.0, "maxY": 326.25}, "class_id": 1, "box_caption": "dental-caries 0.138", "scores": {"class_score": 0.1375732421875}, "domain": "pixel"}, {"position": {"minX": 323.0, "minY": 209.375, "maxX": 411.0, "maxY": 326.25}, "class_id": 0, "box_caption": "bone-loss 0.137", "scores": {"class_score": 0.1368408203125}, "domain": "pixel"}, {"position": {"minX": 152.125, "minY": 114.75, "maxX": 265.75, "maxY": 244.5}, "class_id": 1, "box_caption": "dental-caries 0.130", "scores": {"class_score": 0.1300048828125}, "domain": "pixel"}, {"position": {"minX": 152.125, "minY": 114.75, "maxX": 265.75, "maxY": 244.5}, "class_id": 0, "box_caption": "bone-loss 0.130", "scores": {"class_score": 0.1297607421875}, "domain": "pixel"}, {"position": {"minX": 381.0, "minY": 149.375, "maxX": 480.0, "maxY": 269.0}, "class_id": 1, "box_caption": "dental-caries 0.123", "scores": {"class_score": 0.12286376953125}, "domain": "pixel"}, {"position": {"minX": 157.75, "minY": 253.75, "maxX": 260.0, "maxY": 356.75}, "class_id": 1, "box_caption": "dental-caries 0.123", "scores": {"class_score": 0.122802734375}, "domain": "pixel"}, {"position": {"minX": 381.0, "minY": 149.375, "maxX": 480.0, "maxY": 269.0}, "class_id": 0, "box_caption": "bone-loss 0.122", "scores": {"class_score": 0.1217041015625}, "domain": "pixel"}, {"position": {"minX": 157.75, "minY": 253.75, "maxX": 260.0, "maxY": 356.75}, "class_id": 0, "box_caption": "bone-loss 0.121", "scores": {"class_score": 0.1214599609375}, "domain": "pixel"}, {"position": {"minX": 14.21875, "minY": 115.9375, "maxX": 134.5, "maxY": 244.75}, "class_id": 0, "box_caption": "bone-loss 0.116", "scores": {"class_score": 0.11566162109375}, "domain": "pixel"}, {"position": {"minX": 14.21875, "minY": 115.9375, "maxX": 134.5, "maxY": 244.75}, "class_id": 1, "box_caption": "dental-caries 0.113", "scores": {"class_score": 0.11273193359375}, "domain": "pixel"}, {"position": {"minX": 126.75, "minY": 279.0, "maxX": 228.75, "maxY": 393.0}, "class_id": 0, "box_caption": "bone-loss 0.109", "scores": {"class_score": 0.1090087890625}, "domain": "pixel"}, {"position": {"minX": 189.0, "minY": 365.0, "maxX": 292.75, "maxY": 490.0}, "class_id": 0, "box_caption": "bone-loss 0.108", "scores": {"class_score": 0.10797119140625}, "domain": "pixel"}, {"position": {"minX": -35.625, "minY": 83.5, "maxX": 66.0, "maxY": 204.5}, "class_id": 0, "box_caption": "bone-loss 0.108", "scores": {"class_score": 0.10791015625}, "domain": "pixel"}, {"position": {"minX": 189.0, "minY": 365.0, "maxX": 292.75, "maxY": 490.0}, "class_id": 1, "box_caption": "dental-caries 0.108", "scores": {"class_score": 0.10784912109375}, "domain": "pixel"}, {"position": {"minX": 126.75, "minY": 279.0, "maxX": 228.75, "maxY": 393.0}, "class_id": 1, "box_caption": "dental-caries 0.108", "scores": {"class_score": 0.10772705078125}, "domain": "pixel"}, {"position": {"minX": -35.625, "minY": 83.5, "maxX": 66.0, "maxY": 204.5}, "class_id": 1, "box_caption": "dental-caries 0.107", "scores": {"class_score": 0.1068115234375}, "domain": "pixel"}, {"position": {"minX": 156.25, "minY": 180.5, "maxX": 262.0, "maxY": 302.0}, "class_id": 1, "box_caption": "dental-caries 0.090", "scores": {"class_score": 0.09033203125}, "domain": "pixel"}, {"position": {"minX": 382.0, "minY": 204.25, "maxX": 480.0, "maxY": 333.75}, "class_id": 1, "box_caption": "dental-caries 0.090", "scores": {"class_score": 0.08966064453125}, "domain": "pixel"}, {"position": {"minX": 382.0, "minY": 204.25, "maxX": 480.0, "maxY": 333.75}, "class_id": 0, "box_caption": "bone-loss 0.090", "scores": {"class_score": 0.089599609375}, "domain": "pixel"}, {"position": {"minX": 158.25, "minY": 309.75, "maxX": 258.25, "maxY": 417.25}, "class_id": 1, "box_caption": "dental-caries 0.089", "scores": {"class_score": 0.08935546875}, "domain": "pixel"}, {"position": {"minX": 156.25, "minY": 180.5, "maxX": 262.0, "maxY": 302.0}, "class_id": 0, "box_caption": "bone-loss 0.089", "scores": {"class_score": 0.08905029296875}, "domain": "pixel"}, {"position": {"minX": 158.25, "minY": 309.75, "maxX": 258.25, "maxY": 417.25}, "class_id": 0, "box_caption": "bone-loss 0.088", "scores": {"class_score": 0.08782958984375}, "domain": "pixel"}, {"position": {"minX": 284.5, "minY": 312.0, "maxX": 387.0, "maxY": 419.5}, "class_id": 1, "box_caption": "dental-caries 0.083", "scores": {"class_score": 0.08258056640625}, "domain": "pixel"}, {"position": {"minX": 284.5, "minY": 312.0, "maxX": 387.0, "maxY": 419.5}, "class_id": 0, "box_caption": "bone-loss 0.082", "scores": {"class_score": 0.08160400390625}, "domain": "pixel"}, {"position": {"minX": 159.75, "minY": 350.0, "maxX": 256.5, "maxY": 465.5}, "class_id": 1, "box_caption": "dental-caries 0.077", "scores": {"class_score": 0.07745361328125}, "domain": "pixel"}, {"position": {"minX": 159.75, "minY": 350.0, "maxX": 256.5, "maxY": 465.5}, "class_id": 0, "box_caption": "bone-loss 0.077", "scores": {"class_score": 0.07659912109375}, "domain": "pixel"}, {"position": {"minX": 343.25, "minY": -48.875, "maxX": 456.25, "maxY": 76.6875}, "class_id": 1, "box_caption": "dental-caries 0.073", "scores": {"class_score": 0.0732421875}, "domain": "pixel"}, {"position": {"minX": 343.25, "minY": -48.875, "maxX": 456.25, "maxY": 76.6875}, "class_id": 0, "box_caption": "bone-loss 0.072", "scores": {"class_score": 0.0721435546875}, "domain": "pixel"}, {"position": {"minX": 377.75, "minY": 52.3125, "maxX": 485.25, "maxY": 189.5}, "class_id": 0, "box_caption": "bone-loss 0.065", "scores": {"class_score": 0.06512451171875}, "domain": "pixel"}, {"position": {"minX": 377.75, "minY": 52.3125, "maxX": 485.25, "maxY": 189.5}, "class_id": 1, "box_caption": "dental-caries 0.065", "scores": {"class_score": 0.06475830078125}, "domain": "pixel"}, {"position": {"minX": 217.375, "minY": 406.5, "maxX": 319.5, "maxY": 520.0}, "class_id": 0, "box_caption": "bone-loss 0.063", "scores": {"class_score": 0.06256103515625}, "domain": "pixel"}, {"position": {"minX": 217.375, "minY": 406.5, "maxX": 319.5, "maxY": 520.0}, "class_id": 1, "box_caption": "dental-caries 0.063", "scores": {"class_score": 0.06256103515625}, "domain": "pixel"}, {"position": {"minX": 354.0, "minY": 242.875, "maxX": 446.0, "maxY": 367.0}, "class_id": 1, "box_caption": "dental-caries 0.061", "scores": {"class_score": 0.061065673828125}, "domain": "pixel"}, {"position": {"minX": 354.0, "minY": 242.875, "maxX": 446.0, "maxY": 367.0}, "class_id": 0, "box_caption": "bone-loss 0.060", "scores": {"class_score": 0.060455322265625}, "domain": "pixel"}, {"position": {"minX": 125.375, "minY": 366.5, "maxX": 233.625, "maxY": 487.5}, "class_id": 0, "box_caption": "bone-loss 0.060", "scores": {"class_score": 0.059906005859375}, "domain": "pixel"}, {"position": {"minX": 125.375, "minY": 366.5, "maxX": 233.625, "maxY": 487.5}, "class_id": 1, "box_caption": "dental-caries 0.059", "scores": {"class_score": 0.059295654296875}, "domain": "pixel"}, {"position": {"minX": 82.625, "minY": 114.9375, "maxX": 207.375, "maxY": 245.75}, "class_id": 0, "box_caption": "bone-loss 0.058", "scores": {"class_score": 0.05792236328125}, "domain": "pixel"}, {"position": {"minX": 82.625, "minY": 114.9375, "maxX": 207.375, "maxY": 245.75}, "class_id": 1, "box_caption": "dental-caries 0.057", "scores": {"class_score": 0.056640625}, "domain": "pixel"}, {"position": {"minX": 21.28125, "minY": 184.5, "maxX": 129.5, "maxY": 295.5}, "class_id": 0, "box_caption": "bone-loss 0.049", "scores": {"class_score": 0.04852294921875}, "domain": "pixel"}, {"position": {"minX": 24.90625, "minY": 279.5, "maxX": 129.5, "maxY": 392.5}, "class_id": 0, "box_caption": "bone-loss 0.048", "scores": {"class_score": 0.0482177734375}, "domain": "pixel"}, {"position": {"minX": 21.28125, "minY": 184.5, "maxX": 129.5, "maxY": 295.5}, "class_id": 1, "box_caption": "dental-caries 0.047", "scores": {"class_score": 0.04730224609375}, "domain": "pixel"}, {"position": {"minX": 24.90625, "minY": 279.5, "maxX": 129.5, "maxY": 392.5}, "class_id": 1, "box_caption": "dental-caries 0.047", "scores": {"class_score": 0.046661376953125}, "domain": "pixel"}, {"position": {"minX": -1.21875, "minY": 148.5, "maxX": 99.25, "maxY": 270.25}, "class_id": 0, "box_caption": "bone-loss 0.045", "scores": {"class_score": 0.0450439453125}, "domain": "pixel"}, {"position": {"minX": -38.40625, "minY": -43.6875, "maxX": 71.0, "maxY": 73.125}, "class_id": 0, "box_caption": "bone-loss 0.044", "scores": {"class_score": 0.043731689453125}, "domain": "pixel"}, {"position": {"minX": -1.21875, "minY": 148.5, "maxX": 99.25, "maxY": 270.25}, "class_id": 1, "box_caption": "dental-caries 0.043", "scores": {"class_score": 0.043121337890625}, "domain": "pixel"}, {"position": {"minX": -38.40625, "minY": -43.6875, "maxX": 71.0, "maxY": 73.125}, "class_id": 1, "box_caption": "dental-caries 0.043", "scores": {"class_score": 0.0430908203125}, "domain": "pixel"}, {"position": {"minX": 120.125, "minY": 147.75, "maxX": 235.375, "maxY": 266.75}, "class_id": 1, "box_caption": "dental-caries 0.041", "scores": {"class_score": 0.0413818359375}, "domain": "pixel"}, {"position": {"minX": 120.125, "minY": 147.75, "maxX": 235.375, "maxY": 266.75}, "class_id": 0, "box_caption": "bone-loss 0.041", "scores": {"class_score": 0.04132080078125}, "domain": "pixel"}, {"position": {"minX": 313.5, "minY": 345.0, "maxX": 419.5, "maxY": 466.5}, "class_id": 1, "box_caption": "dental-caries 0.040", "scores": {"class_score": 0.03973388671875}, "domain": "pixel"}, {"position": {"minX": 313.5, "minY": 345.0, "maxX": 419.5, "maxY": 466.5}, "class_id": 0, "box_caption": "bone-loss 0.039", "scores": {"class_score": 0.039459228515625}, "domain": "pixel"}, {"position": {"minX": 320.0, "minY": 272.5, "maxX": 415.5, "maxY": 400.5}, "class_id": 0, "box_caption": "bone-loss 0.038", "scores": {"class_score": 0.037750244140625}, "domain": "pixel"}, {"position": {"minX": 320.0, "minY": 272.5, "maxX": 415.5, "maxY": 400.5}, "class_id": 1, "box_caption": "dental-caries 0.038", "scores": {"class_score": 0.037567138671875}, "domain": "pixel"}, {"position": {"minX": 279.5, "minY": 406.0, "maxX": 387.5, "maxY": 521.0}, "class_id": 1, "box_caption": "dental-caries 0.035", "scores": {"class_score": 0.034637451171875}, "domain": "pixel"}, {"position": {"minX": 279.5, "minY": 406.0, "maxX": 387.5, "maxY": 521.0}, "class_id": 0, "box_caption": "bone-loss 0.034", "scores": {"class_score": 0.034271240234375}, "domain": "pixel"}, {"position": {"minX": 378.0, "minY": -13.8125, "maxX": 487.0, "maxY": 114.5625}, "class_id": 0, "box_caption": "bone-loss 0.034", "scores": {"class_score": 0.033599853515625}, "domain": "pixel"}, {"position": {"minX": 378.0, "minY": -13.8125, "maxX": 487.0, "maxY": 114.5625}, "class_id": 1, "box_caption": "dental-caries 0.033", "scores": {"class_score": 0.033447265625}, "domain": "pixel"}, {"position": {"minX": -30.46875, "minY": 184.75, "maxX": 62.96875, "maxY": 294.0}, "class_id": 0, "box_caption": "bone-loss 0.028", "scores": {"class_score": 0.028289794921875}, "domain": "pixel"}, {"position": {"minX": -30.46875, "minY": 184.75, "maxX": 62.96875, "maxY": 294.0}, "class_id": 1, "box_caption": "dental-caries 0.028", "scores": {"class_score": 0.028106689453125}, "domain": "pixel"}, {"position": {"minX": 94.3125, "minY": 309.5, "maxX": 194.25, "maxY": 419.5}, "class_id": 1, "box_caption": "dental-caries 0.025", "scores": {"class_score": 0.025360107421875}, "domain": "pixel"}, {"position": {"minX": 94.3125, "minY": 309.5, "maxX": 194.25, "maxY": 419.5}, "class_id": 0, "box_caption": "bone-loss 0.025", "scores": {"class_score": 0.0249786376953125}, "domain": "pixel"}, {"position": {"minX": 62.34375, "minY": 183.625, "maxX": 175.5, "maxY": 298.0}, "class_id": 0, "box_caption": "bone-loss 0.024", "scores": {"class_score": 0.0244140625}, "domain": "pixel"}, {"position": {"minX": 62.34375, "minY": 183.625, "maxX": 175.5, "maxY": 298.0}, "class_id": 1, "box_caption": "dental-caries 0.024", "scores": {"class_score": 0.023834228515625}, "domain": "pixel"}, {"position": {"minX": 21.09375, "minY": 370.0, "maxX": 130.25, "maxY": 490.0}, "class_id": 0, "box_caption": "bone-loss 0.023", "scores": {"class_score": 0.023468017578125}, "domain": "pixel"}, {"position": {"minX": 21.09375, "minY": 370.0, "maxX": 130.25, "maxY": 490.0}, "class_id": 1, "box_caption": "dental-caries 0.022", "scores": {"class_score": 0.0223846435546875}, "domain": "pixel"}, {"position": {"minX": 123.875, "minY": 213.0, "maxX": 231.125, "maxY": 325.0}, "class_id": 1, "box_caption": "dental-caries 0.022", "scores": {"class_score": 0.0216217041015625}, "domain": "pixel"}, {"position": {"minX": 90.875, "minY": 253.125, "maxX": 196.375, "maxY": 356.75}, "class_id": 1, "box_caption": "dental-caries 0.021", "scores": {"class_score": 0.021270751953125}, "domain": "pixel"}, {"position": {"minX": 62.46875, "minY": 252.125, "maxX": 176.625, "maxY": 358.5}, "class_id": 0, "box_caption": "bone-loss 0.021", "scores": {"class_score": 0.02105712890625}, "domain": "pixel"}, {"position": {"minX": 123.875, "minY": 213.0, "maxX": 231.125, "maxY": 325.0}, "class_id": 0, "box_caption": "bone-loss 0.021", "scores": {"class_score": 0.0209808349609375}, "domain": "pixel"}, {"position": {"minX": 414.0, "minY": 176.0, "maxX": 512.0, "maxY": 304.25}, "class_id": 1, "box_caption": "dental-caries 0.019", "scores": {"class_score": 0.0188751220703125}, "domain": "pixel"}, {"position": {"minX": 414.0, "minY": 176.0, "maxX": 512.0, "maxY": 304.25}, "class_id": 0, "box_caption": "bone-loss 0.019", "scores": {"class_score": 0.01861572265625}, "domain": "pixel"}, {"position": {"minX": 63.5625, "minY": 346.75, "maxX": 172.5, "maxY": 459.25}, "class_id": 0, "box_caption": "bone-loss 0.018", "scores": {"class_score": 0.0184173583984375}, "domain": "pixel"}, {"position": {"minX": -27.875, "minY": 279.75, "maxX": 62.8125, "maxY": 390.75}, "class_id": 0, "box_caption": "bone-loss 0.018", "scores": {"class_score": 0.01837158203125}, "domain": "pixel"}, {"position": {"minX": 349.75, "minY": 301.0, "maxX": 449.75, "maxY": 426.0}, "class_id": 1, "box_caption": "dental-caries 0.018", "scores": {"class_score": 0.0180816650390625}, "domain": "pixel"}, {"position": {"minX": -27.875, "minY": 279.75, "maxX": 62.8125, "maxY": 390.75}, "class_id": 1, "box_caption": "dental-caries 0.018", "scores": {"class_score": 0.018035888671875}, "domain": "pixel"}, {"position": {"minX": 63.5625, "minY": 346.75, "maxX": 172.5, "maxY": 459.25}, "class_id": 1, "box_caption": "dental-caries 0.018", "scores": {"class_score": 0.0180206298828125}, "domain": "pixel"}, {"position": {"minX": 1.1875, "minY": 249.0, "maxX": 96.25, "maxY": 362.5}, "class_id": 0, "box_caption": "bone-loss 0.018", "scores": {"class_score": 0.017669677734375}, "domain": "pixel"}, {"position": {"minX": 410.0, "minY": 73.5625, "maxX": 517.0, "maxY": 211.5}, "class_id": 1, "box_caption": "dental-caries 0.018", "scores": {"class_score": 0.0176239013671875}, "domain": "pixel"}, {"position": {"minX": 349.75, "minY": 301.0, "maxX": 449.75, "maxY": 426.0}, "class_id": 0, "box_caption": "bone-loss 0.018", "scores": {"class_score": 0.0175933837890625}, "domain": "pixel"}, {"position": {"minX": 410.0, "minY": 73.5625, "maxX": 517.0, "maxY": 211.5}, "class_id": 0, "box_caption": "bone-loss 0.017", "scores": {"class_score": 0.0173492431640625}, "domain": "pixel"}, {"position": {"minX": 380.5, "minY": 263.5, "maxX": 485.5, "maxY": 411.0}, "class_id": 0, "box_caption": "bone-loss 0.017", "scores": {"class_score": 0.017333984375}, "domain": "pixel"}, {"position": {"minX": 380.5, "minY": 263.5, "maxX": 485.5, "maxY": 411.0}, "class_id": 1, "box_caption": "dental-caries 0.017", "scores": {"class_score": 0.016937255859375}, "domain": "pixel"}, {"position": {"minX": 1.1875, "minY": 249.0, "maxX": 96.25, "maxY": 362.5}, "class_id": 1, "box_caption": "dental-caries 0.017", "scores": {"class_score": 0.016845703125}, "domain": "pixel"}, {"position": {"minX": 158.25, "minY": 410.25, "maxX": 257.0, "maxY": 518.0}, "class_id": 1, "box_caption": "dental-caries 0.015", "scores": {"class_score": 0.015380859375}, "domain": "pixel"}, {"position": {"minX": 158.25, "minY": 410.25, "maxX": 257.0, "maxY": 518.0}, "class_id": 0, "box_caption": "bone-loss 0.015", "scores": {"class_score": 0.01491546630859375}, "domain": "pixel"}, {"position": {"minX": 463.75, "minY": 188.875, "maxX": 529.0, "maxY": 291.5}, "class_id": 0, "box_caption": "bone-loss 0.014", "scores": {"class_score": 0.0143890380859375}, "domain": "pixel"}, {"position": {"minX": 490.0, "minY": 415.25, "maxX": 560.0, "maxY": 511.75}, "class_id": 1, "box_caption": "dental-caries 0.014", "scores": {"class_score": 0.01415252685546875}, "domain": "pixel"}, {"position": {"minX": 463.75, "minY": 188.875, "maxX": 529.0, "maxY": 291.5}, "class_id": 1, "box_caption": "dental-caries 0.014", "scores": {"class_score": 0.0141448974609375}, "domain": "pixel"}, {"position": {"minX": 105.1875, "minY": 417.0, "maxX": 185.25, "maxY": 512.0}, "class_id": 1, "box_caption": "dental-caries 0.014", "scores": {"class_score": 0.01407623291015625}, "domain": "pixel"}, {"position": {"minX": 490.0, "minY": 415.25, "maxX": 560.0, "maxY": 511.75}, "class_id": 0, "box_caption": "bone-loss 0.014", "scores": {"class_score": 0.014007568359375}, "domain": "pixel"}, {"position": {"minX": 495.0, "minY": 187.375, "maxX": 561.0, "maxY": 291.25}, "class_id": 1, "box_caption": "dental-caries 0.014", "scores": {"class_score": 0.013946533203125}, "domain": "pixel"}, {"position": {"minX": 202.75, "minY": 417.0, "maxX": 278.25, "maxY": 511.0}, "class_id": 1, "box_caption": "dental-caries 0.014", "scores": {"class_score": 0.01393890380859375}, "domain": "pixel"}, {"position": {"minX": 558.0, "minY": 412.0, "maxX": 627.0, "maxY": 516.0}, "class_id": 1, "box_caption": "dental-caries 0.014", "scores": {"class_score": 0.01385498046875}, "domain": "pixel"}, {"position": {"minX": 591.0, "minY": 412.25, "maxX": 656.0, "maxY": 518.0}, "class_id": 1, "box_caption": "dental-caries 0.014", "scores": {"class_score": 0.01380157470703125}, "domain": "pixel"}, {"position": {"minX": 227.0, "minY": 62.40625, "maxX": 316.0, "maxY": 172.375}, "class_id": 1, "box_caption": "dental-caries 0.014", "scores": {"class_score": 0.01374053955078125}, "domain": "pixel"}, {"position": {"minX": 202.75, "minY": 417.0, "maxX": 278.25, "maxY": 511.0}, "class_id": 0, "box_caption": "bone-loss 0.014", "scores": {"class_score": 0.0137176513671875}, "domain": "pixel"}, {"position": {"minX": 105.1875, "minY": 417.0, "maxX": 185.25, "maxY": 512.0}, "class_id": 0, "box_caption": "bone-loss 0.014", "scores": {"class_score": 0.013702392578125}, "domain": "pixel"}, {"position": {"minX": 558.0, "minY": 412.0, "maxX": 627.0, "maxY": 516.0}, "class_id": 0, "box_caption": "bone-loss 0.014", "scores": {"class_score": 0.013702392578125}, "domain": "pixel"}, {"position": {"minX": 593.0, "minY": 184.125, "maxX": 655.0, "maxY": 296.75}, "class_id": 1, "box_caption": "dental-caries 0.014", "scores": {"class_score": 0.01366424560546875}, "domain": "pixel"}, {"position": {"minX": 96.6875, "minY": 86.875, "maxX": 192.0, "maxY": 200.125}, "class_id": 0, "box_caption": "bone-loss 0.014", "scores": {"class_score": 0.0136260986328125}, "domain": "pixel"}, {"position": {"minX": 96.6875, "minY": 86.875, "maxX": 192.0, "maxY": 200.125}, "class_id": 1, "box_caption": "dental-caries 0.014", "scores": {"class_score": 0.01358795166015625}, "domain": "pixel"}, {"position": {"minX": 463.5, "minY": 127.125, "maxX": 530.0, "maxY": 233.125}, "class_id": 1, "box_caption": "dental-caries 0.014", "scores": {"class_score": 0.0135498046875}, "domain": "pixel"}, {"position": {"minX": 495.0, "minY": 187.375, "maxX": 561.0, "maxY": 291.25}, "class_id": 0, "box_caption": "bone-loss 0.014", "scores": {"class_score": 0.01354217529296875}, "domain": "pixel"}, {"position": {"minX": 591.0, "minY": 412.25, "maxX": 656.0, "maxY": 518.0}, "class_id": 0, "box_caption": "bone-loss 0.014", "scores": {"class_score": 0.0135040283203125}, "domain": "pixel"}, {"position": {"minX": 345.0, "minY": 361.25, "maxX": 454.5, "maxY": 492.25}, "class_id": 1, "box_caption": "dental-caries 0.013", "scores": {"class_score": 0.013458251953125}, "domain": "pixel"}, {"position": {"minX": 227.0, "minY": 62.40625, "maxX": 316.0, "maxY": 172.375}, "class_id": 0, "box_caption": "bone-loss 0.013", "scores": {"class_score": 0.013427734375}, "domain": "pixel"}, {"position": {"minX": 395.5, "minY": 127.0, "maxX": 467.0, "maxY": 231.75}, "class_id": 1, "box_caption": "dental-caries 0.013", "scores": {"class_score": 0.013427734375}, "domain": "pixel"}, {"position": {"minX": 345.0, "minY": 361.25, "maxX": 454.5, "maxY": 492.25}, "class_id": 0, "box_caption": "bone-loss 0.013", "scores": {"class_score": 0.013397216796875}, "domain": "pixel"}, {"position": {"minX": 463.5, "minY": 127.125, "maxX": 530.0, "maxY": 233.125}, "class_id": 0, "box_caption": "bone-loss 0.013", "scores": {"class_score": 0.01338958740234375}, "domain": "pixel"}, {"position": {"minX": 593.0, "minY": 184.125, "maxX": 655.0, "maxY": 296.75}, "class_id": 0, "box_caption": "bone-loss 0.013", "scores": {"class_score": 0.013336181640625}, "domain": "pixel"}, {"position": {"minX": 528.5, "minY": 413.0, "maxX": 592.5, "maxY": 514.0}, "class_id": 1, "box_caption": "dental-caries 0.013", "scores": {"class_score": 0.013336181640625}, "domain": "pixel"}, {"position": {"minX": 395.5, "minY": 127.0, "maxX": 467.0, "maxY": 231.75}, "class_id": 0, "box_caption": "bone-loss 0.013", "scores": {"class_score": 0.01332855224609375}, "domain": "pixel"}, {"position": {"minX": 590.5, "minY": 124.875, "maxX": 657.5, "maxY": 242.375}, "class_id": 1, "box_caption": "dental-caries 0.013", "scores": {"class_score": 0.01323699951171875}, "domain": "pixel"}, {"position": {"minX": 430.75, "minY": 159.75, "maxX": 497.75, "maxY": 260.0}, "class_id": 1, "box_caption": "dental-caries 0.013", "scores": {"class_score": 0.01320648193359375}, "domain": "pixel"}, {"position": {"minX": 430.25, "minY": 215.0, "maxX": 498.25, "maxY": 321.5}, "class_id": 1, "box_caption": "dental-caries 0.013", "scores": {"class_score": 0.0131378173828125}, "domain": "pixel"}, {"position": {"minX": 139.375, "minY": 319.0, "maxX": 216.875, "maxY": 413.0}, "class_id": 1, "box_caption": "dental-caries 0.013", "scores": {"class_score": 0.013092041015625}, "domain": "pixel"}, {"position": {"minX": 528.5, "minY": 413.0, "maxX": 592.5, "maxY": 514.0}, "class_id": 0, "box_caption": "bone-loss 0.013", "scores": {"class_score": 0.01308441162109375}, "domain": "pixel"}, {"position": {"minX": 590.5, "minY": 124.875, "maxX": 657.5, "maxY": 242.375}, "class_id": 0, "box_caption": "bone-loss 0.013", "scores": {"class_score": 0.013031005859375}, "domain": "pixel"}, {"position": {"minX": 430.75, "minY": 159.75, "maxX": 497.75, "maxY": 260.0}, "class_id": 0, "box_caption": "bone-loss 0.013", "scores": {"class_score": 0.01302337646484375}, "domain": "pixel"}, {"position": {"minX": 328.75, "minY": 415.75, "maxX": 405.75, "maxY": 514.0}, "class_id": 1, "box_caption": "dental-caries 0.013", "scores": {"class_score": 0.0130157470703125}, "domain": "pixel"}, {"position": {"minX": 493.5, "minY": 126.75, "maxX": 560.5, "maxY": 236.5}, "class_id": 1, "box_caption": "dental-caries 0.013", "scores": {"class_score": 0.01291656494140625}, "domain": "pixel"}, {"position": {"minX": 496.5, "minY": 285.75, "maxX": 558.5, "maxY": 390.75}, "class_id": 1, "box_caption": "dental-caries 0.013", "scores": {"class_score": 0.01290130615234375}, "domain": "pixel"}, {"position": {"minX": 589.0, "minY": -2.09375, "maxX": 660.0, "maxY": 102.625}, "class_id": 1, "box_caption": "dental-caries 0.013", "scores": {"class_score": 0.0128936767578125}, "domain": "pixel"}, {"position": {"minX": 139.375, "minY": 319.0, "maxX": 216.875, "maxY": 413.0}, "class_id": 0, "box_caption": "bone-loss 0.013", "scores": {"class_score": 0.01287841796875}, "domain": "pixel"}, {"position": {"minX": 328.75, "minY": 415.75, "maxX": 405.75, "maxY": 514.0}, "class_id": 0, "box_caption": "bone-loss 0.013", "scores": {"class_score": 0.01287078857421875}, "domain": "pixel"}, {"position": {"minX": 139.125, "minY": 451.5, "maxX": 215.375, "maxY": 541.0}, "class_id": 1, "box_caption": "dental-caries 0.013", "scores": {"class_score": 0.01284027099609375}, "domain": "pixel"}, {"position": {"minX": 463.25, "minY": 450.0, "maxX": 531.5, "maxY": 543.0}, "class_id": 1, "box_caption": "dental-caries 0.013", "scores": {"class_score": 0.01282501220703125}, "domain": "pixel"}, {"position": {"minX": 103.625, "minY": 225.75, "maxX": 183.375, "maxY": 314.75}, "class_id": 1, "box_caption": "dental-caries 0.013", "scores": {"class_score": 0.0128173828125}, "domain": "pixel"}, {"position": {"minX": 529.0, "minY": 184.75, "maxX": 592.0, "maxY": 294.25}, "class_id": 1, "box_caption": "dental-caries 0.013", "scores": {"class_score": 0.0128021240234375}, "domain": "pixel"}, {"position": {"minX": 364.75, "minY": 415.5, "maxX": 436.25, "maxY": 513.5}, "class_id": 1, "box_caption": "dental-caries 0.013", "scores": {"class_score": 0.0127716064453125}, "domain": "pixel"}, {"position": {"minX": 463.25, "minY": 450.0, "maxX": 531.5, "maxY": 543.0}, "class_id": 0, "box_caption": "bone-loss 0.013", "scores": {"class_score": 0.01274871826171875}, "domain": "pixel"}, {"position": {"minX": 430.25, "minY": 215.0, "maxX": 498.25, "maxY": 321.5}, "class_id": 0, "box_caption": "bone-loss 0.013", "scores": {"class_score": 0.01273345947265625}, "domain": "pixel"}, {"position": {"minX": 200.25, "minY": 258.5, "maxX": 279.75, "maxY": 350.5}, "class_id": 1, "box_caption": "dental-caries 0.013", "scores": {"class_score": 0.01271820068359375}, "domain": "pixel"}, {"position": {"minX": 171.375, "minY": 452.5, "maxX": 244.375, "maxY": 540.5}, "class_id": 1, "box_caption": "dental-caries 0.013", "scores": {"class_score": 0.01270294189453125}, "domain": "pixel"}, {"position": {"minX": 529.0, "minY": 184.75, "maxX": 592.0, "maxY": 294.25}, "class_id": 0, "box_caption": "bone-loss 0.013", "scores": {"class_score": 0.0126800537109375}, "domain": "pixel"}, {"position": {"minX": 326.5, "minY": 91.0, "maxX": 409.0, "maxY": 199.0}, "class_id": 1, "box_caption": "dental-caries 0.013", "scores": {"class_score": 0.01263427734375}, "domain": "pixel"}, {"position": {"minX": 103.625, "minY": 225.75, "maxX": 183.375, "maxY": 314.75}, "class_id": 0, "box_caption": "bone-loss 0.013", "scores": {"class_score": 0.0126190185546875}, "domain": "pixel"}, {"position": {"minX": 496.5, "minY": 285.75, "maxX": 558.5, "maxY": 390.75}, "class_id": 0, "box_caption": "bone-loss 0.013", "scores": {"class_score": 0.0125732421875}, "domain": "pixel"}, {"position": {"minX": 139.125, "minY": 451.5, "maxX": 215.375, "maxY": 541.0}, "class_id": 0, "box_caption": "bone-loss 0.013", "scores": {"class_score": 0.0125579833984375}, "domain": "pixel"}, {"position": {"minX": 364.75, "minY": 415.5, "maxX": 436.25, "maxY": 513.5}, "class_id": 0, "box_caption": "bone-loss 0.013", "scores": {"class_score": 0.0125579833984375}, "domain": "pixel"}, {"position": {"minX": 135.375, "minY": 259.0, "maxX": 219.375, "maxY": 349.5}, "class_id": 1, "box_caption": "dental-caries 0.013", "scores": {"class_score": 0.01251220703125}, "domain": "pixel"}, {"position": {"minX": 557.0, "minY": 86.0, "maxX": 627.0, "maxY": 199.75}, "class_id": 1, "box_caption": "dental-caries 0.012", "scores": {"class_score": 0.012481689453125}, "domain": "pixel"}, {"position": {"minX": 171.375, "minY": 452.5, "maxX": 244.375, "maxY": 540.5}, "class_id": 0, "box_caption": "bone-loss 0.012", "scores": {"class_score": 0.01247406005859375}, "domain": "pixel"}, {"position": {"minX": 430.25, "minY": 282.75, "maxX": 497.25, "maxY": 394.25}, "class_id": 1, "box_caption": "dental-caries 0.012", "scores": {"class_score": 0.01247406005859375}, "domain": "pixel"}, {"position": {"minX": 395.5, "minY": 416.5, "maxX": 470.0, "maxY": 513.0}, "class_id": 1, "box_caption": "dental-caries 0.012", "scores": {"class_score": 0.01244354248046875}, "domain": "pixel"}, {"position": {"minX": 169.0, "minY": 222.375, "maxX": 247.5, "maxY": 316.5}, "class_id": 1, "box_caption": "dental-caries 0.012", "scores": {"class_score": 0.01242828369140625}, "domain": "pixel"}, {"position": {"minX": 326.5, "minY": 91.0, "maxX": 409.0, "maxY": 199.0}, "class_id": 0, "box_caption": "bone-loss 0.012", "scores": {"class_score": 0.012420654296875}, "domain": "pixel"}, {"position": {"minX": 493.5, "minY": 126.75, "maxX": 560.5, "maxY": 236.5}, "class_id": 0, "box_caption": "bone-loss 0.012", "scores": {"class_score": 0.01241302490234375}, "domain": "pixel"}, {"position": {"minX": 395.5, "minY": 416.5, "maxX": 470.0, "maxY": 513.0}, "class_id": 0, "box_caption": "bone-loss 0.012", "scores": {"class_score": 0.01241302490234375}, "domain": "pixel"}, {"position": {"minX": 70.5625, "minY": 158.75, "maxX": 162.5, "maxY": 256.75}, "class_id": 1, "box_caption": "dental-caries 0.012", "scores": {"class_score": 0.01236724853515625}, "domain": "pixel"}, {"position": {"minX": 461.75, "minY": 61.46875, "maxX": 530.5, "maxY": 176.0}, "class_id": 1, "box_caption": "dental-caries 0.012", "scores": {"class_score": 0.01235198974609375}, "domain": "pixel"}, {"position": {"minX": 169.0, "minY": 222.375, "maxX": 247.5, "maxY": 316.5}, "class_id": 0, "box_caption": "bone-loss 0.012", "scores": {"class_score": 0.0123443603515625}, "domain": "pixel"}, {"position": {"minX": 200.25, "minY": 258.5, "maxX": 279.75, "maxY": 350.5}, "class_id": 0, "box_caption": "bone-loss 0.012", "scores": {"class_score": 0.01233673095703125}, "domain": "pixel"}, {"position": {"minX": 591.5, "minY": 247.0, "maxX": 654.5, "maxY": 357.5}, "class_id": 1, "box_caption": "dental-caries 0.012", "scores": {"class_score": 0.01233673095703125}, "domain": "pixel"}, {"position": {"minX": 559.5, "minY": 184.375, "maxX": 623.5, "maxY": 295.25}, "class_id": 1, "box_caption": "dental-caries 0.012", "scores": {"class_score": 0.0123291015625}, "domain": "pixel"}, {"position": {"minX": 526.5, "minY": 84.5, "maxX": 592.5, "maxY": 202.0}, "class_id": 1, "box_caption": "dental-caries 0.012", "scores": {"class_score": 0.0123291015625}, "domain": "pixel"}, {"position": {"minX": 34.1875, "minY": 225.75, "maxX": 119.5625, "maxY": 316.25}, "class_id": 1, "box_caption": "dental-caries 0.012", "scores": {"class_score": 0.0123291015625}, "domain": "pixel"}, {"position": {"minX": 463.0, "minY": 285.5, "maxX": 528.0, "maxY": 389.0}, "class_id": 0, "box_caption": "bone-loss 0.012", "scores": {"class_score": 0.01232147216796875}, "domain": "pixel"}, {"position": {"minX": 135.375, "minY": 259.0, "maxX": 219.375, "maxY": 349.5}, "class_id": 0, "box_caption": "bone-loss 0.012", "scores": {"class_score": 0.0123138427734375}, "domain": "pixel"}, {"position": {"minX": 588.5, "minY": 7.53125, "maxX": 659.5, "maxY": 127.25}, "class_id": 0, "box_caption": "bone-loss 0.012", "scores": {"class_score": 0.01230621337890625}, "domain": "pixel"}, {"position": {"minX": 557.0, "minY": 86.0, "maxX": 627.0, "maxY": 199.75}, "class_id": 0, "box_caption": "bone-loss 0.012", "scores": {"class_score": 0.012298583984375}, "domain": "pixel"}, {"position": {"minX": 427.0, "minY": 12.25, "maxX": 501.5, "maxY": 129.625}, "class_id": 1, "box_caption": "dental-caries 0.012", "scores": {"class_score": 0.012298583984375}, "domain": "pixel"}, {"position": {"minX": 624.5, "minY": 184.625, "maxX": 687.5, "maxY": 294.5}, "class_id": 0, "box_caption": "bone-loss 0.012", "scores": {"class_score": 0.01226806640625}, "domain": "pixel"}, {"position": {"minX": 588.5, "minY": 61.90625, "maxX": 659.5, "maxY": 188.375}, "class_id": 1, "box_caption": "dental-caries 0.012", "scores": {"class_score": 0.01226043701171875}, "domain": "pixel"}, {"position": {"minX": 362.0, "minY": 126.3125, "maxX": 438.0, "maxY": 234.0}, "class_id": 1, "box_caption": "dental-caries 0.012", "scores": {"class_score": 0.01226043701171875}, "domain": "pixel"}, {"position": {"minX": 490.5, "minY": -5.1875, "maxX": 562.5, "maxY": 104.1875}, "class_id": 1, "box_caption": "dental-caries 0.012", "scores": {"class_score": 0.01222991943359375}, "domain": "pixel"}, {"position": {"minX": 34.1875, "minY": 225.75, "maxX": 119.5625, "maxY": 316.25}, "class_id": 0, "box_caption": "bone-loss 0.012", "scores": {"class_score": 0.01221466064453125}, "domain": "pixel"}, {"position": {"minX": 233.75, "minY": 450.0, "maxX": 307.25, "maxY": 544.0}, "class_id": 0, "box_caption": "bone-loss 0.012", "scores": {"class_score": 0.01219940185546875}, "domain": "pixel"}, {"position": {"minX": 530.0, "minY": 251.0, "maxX": 591.0, "maxY": 356.0}, "class_id": 1, "box_caption": "dental-caries 0.012", "scores": {"class_score": 0.012176513671875}, "domain": "pixel"}, {"position": {"minX": 461.75, "minY": 61.46875, "maxX": 530.5, "maxY": 176.0}, "class_id": 0, "box_caption": "bone-loss 0.012", "scores": {"class_score": 0.0121612548828125}, "domain": "pixel"}, {"position": {"minX": 76.125, "minY": 450.75, "maxX": 155.125, "maxY": 541.5}, "class_id": 1, "box_caption": "dental-caries 0.012", "scores": {"class_score": 0.01214599609375}, "domain": "pixel"}, {"position": {"minX": 70.5625, "minY": 158.75, "maxX": 162.5, "maxY": 256.75}, "class_id": 0, "box_caption": "bone-loss 0.012", "scores": {"class_score": 0.01213836669921875}, "domain": "pixel"}, {"position": {"minX": 265.75, "minY": 449.0, "maxX": 343.25, "maxY": 544.5}, "class_id": 1, "box_caption": "dental-caries 0.012", "scores": {"class_score": 0.01212310791015625}, "domain": "pixel"}, {"position": {"minX": 362.0, "minY": 126.3125, "maxX": 438.0, "maxY": 234.0}, "class_id": 0, "box_caption": "bone-loss 0.012", "scores": {"class_score": 0.01212310791015625}, "domain": "pixel"}, {"position": {"minX": 233.75, "minY": 450.0, "maxX": 307.25, "maxY": 544.0}, "class_id": 1, "box_caption": "dental-caries 0.012", "scores": {"class_score": 0.012115478515625}, "domain": "pixel"}, {"position": {"minX": 464.25, "minY": 256.5, "maxX": 530.0, "maxY": 350.5}, "class_id": 1, "box_caption": "dental-caries 0.012", "scores": {"class_score": 0.0121002197265625}, "domain": "pixel"}, {"position": {"minX": 427.0, "minY": 12.25, "maxX": 501.5, "maxY": 129.625}, "class_id": 0, "box_caption": "bone-loss 0.012", "scores": {"class_score": 0.01209259033203125}, "domain": "pixel"}, {"position": {"minX": 559.5, "minY": 184.375, "maxX": 623.5, "maxY": 295.25}, "class_id": 0, "box_caption": "bone-loss 0.012", "scores": {"class_score": 0.01209259033203125}, "domain": "pixel"}, {"position": {"minX": 526.5, "minY": 84.5, "maxX": 592.5, "maxY": 202.0}, "class_id": 0, "box_caption": "bone-loss 0.012", "scores": {"class_score": 0.0120697021484375}, "domain": "pixel"}, {"position": {"minX": 430.25, "minY": 282.75, "maxX": 497.25, "maxY": 394.25}, "class_id": 0, "box_caption": "bone-loss 0.012", "scores": {"class_score": 0.012054443359375}, "domain": "pixel"}, {"position": {"minX": 428.75, "minY": 416.5, "maxX": 498.25, "maxY": 513.5}, "class_id": 1, "box_caption": "dental-caries 0.012", "scores": {"class_score": 0.0120391845703125}, "domain": "pixel"}, {"position": {"minX": 265.75, "minY": 449.0, "maxX": 343.25, "maxY": 544.5}, "class_id": 0, "box_caption": "bone-loss 0.012", "scores": {"class_score": 0.0120391845703125}, "domain": "pixel"}, {"position": {"minX": 75.625, "minY": 380.5, "maxX": 151.125, "maxY": 481.5}, "class_id": 0, "box_caption": "bone-loss 0.012", "scores": {"class_score": 0.01201629638671875}, "domain": "pixel"}, {"position": {"minX": 624.5, "minY": 184.625, "maxX": 687.5, "maxY": 294.5}, "class_id": 1, "box_caption": "dental-caries 0.012", "scores": {"class_score": 0.011993408203125}, "domain": "pixel"}, {"position": {"minX": 105.75, "minY": 288.0, "maxX": 181.0, "maxY": 383.5}, "class_id": 0, "box_caption": "bone-loss 0.012", "scores": {"class_score": 0.01198577880859375}, "domain": "pixel"}, {"position": {"minX": 397.75, "minY": 311.5, "maxX": 468.75, "maxY": 419.5}, "class_id": 1, "box_caption": "dental-caries 0.012", "scores": {"class_score": 0.0119781494140625}, "domain": "pixel"}, {"position": {"minX": 76.125, "minY": 450.75, "maxX": 155.125, "maxY": 541.5}, "class_id": 0, "box_caption": "bone-loss 0.012", "scores": {"class_score": 0.01195526123046875}, "domain": "pixel"}, {"position": {"minX": 105.75, "minY": 288.0, "maxX": 181.0, "maxY": 383.5}, "class_id": 1, "box_caption": "dental-caries 0.012", "scores": {"class_score": 0.0119476318359375}, "domain": "pixel"}, {"position": {"minX": 428.75, "minY": 416.5, "maxX": 498.25, "maxY": 513.5}, "class_id": 0, "box_caption": "bone-loss 0.012", "scores": {"class_score": 0.01194000244140625}, "domain": "pixel"}, {"position": {"minX": 461.0, "minY": 15.625, "maxX": 531.5, "maxY": 128.375}, "class_id": 1, "box_caption": "dental-caries 0.012", "scores": {"class_score": 0.011932373046875}, "domain": "pixel"}, {"position": {"minX": 530.0, "minY": 251.0, "maxX": 591.0, "maxY": 356.0}, "class_id": 0, "box_caption": "bone-loss 0.012", "scores": {"class_score": 0.011932373046875}, "domain": "pixel"}, {"position": {"minX": 591.5, "minY": 247.0, "maxX": 654.5, "maxY": 357.5}, "class_id": 0, "box_caption": "bone-loss 0.012", "scores": {"class_score": 0.01192474365234375}, "domain": "pixel"}, {"position": {"minX": 492.5, "minY": 61.1875, "maxX": 562.5, "maxY": 177.5}, "class_id": 1, "box_caption": "dental-caries 0.012", "scores": {"class_score": 0.01190185546875}, "domain": "pixel"}, {"position": {"minX": 75.625, "minY": 380.5, "maxX": 151.125, "maxY": 481.5}, "class_id": 1, "box_caption": "dental-caries 0.012", "scores": {"class_score": 0.01189422607421875}, "domain": "pixel"}, {"position": {"minX": 460.5, "minY": 372.5, "maxX": 531.5, "maxY": 483.5}, "class_id": 0, "box_caption": "bone-loss 0.012", "scores": {"class_score": 0.0118255615234375}, "domain": "pixel"}, {"position": {"minX": 490.5, "minY": -5.1875, "maxX": 562.5, "maxY": 104.1875}, "class_id": 0, "box_caption": "bone-loss 0.012", "scores": {"class_score": 0.0118255615234375}, "domain": "pixel"}, {"position": {"minX": 622.0, "minY": 124.625, "maxX": 689.0, "maxY": 237.125}, "class_id": 0, "box_caption": "bone-loss 0.012", "scores": {"class_score": 0.01180267333984375}, "domain": "pixel"}, {"position": {"minX": 588.5, "minY": 61.90625, "maxX": 659.5, "maxY": 188.375}, "class_id": 0, "box_caption": "bone-loss 0.012", "scores": {"class_score": 0.0117950439453125}, "domain": "pixel"}, {"position": {"minX": 8.78125, "minY": 223.0, "maxX": 85.625, "maxY": 318.5}, "class_id": 1, "box_caption": "dental-caries 0.012", "scores": {"class_score": 0.01174163818359375}, "domain": "pixel"}, {"position": {"minX": 8.78125, "minY": 223.0, "maxX": 85.625, "maxY": 318.5}, "class_id": 0, "box_caption": "bone-loss 0.012", "scores": {"class_score": 0.0117340087890625}, "domain": "pixel"}, {"position": {"minX": 396.75, "minY": 350.0, "maxX": 468.75, "maxY": 459.0}, "class_id": 0, "box_caption": "bone-loss 0.012", "scores": {"class_score": 0.0117340087890625}, "domain": "pixel"}, {"position": {"minX": 492.5, "minY": 61.1875, "maxX": 562.5, "maxY": 177.5}, "class_id": 0, "box_caption": "bone-loss 0.012", "scores": {"class_score": 0.01171112060546875}, "domain": "pixel"}, {"position": {"minX": 460.5, "minY": 372.5, "maxX": 531.5, "maxY": 483.5}, "class_id": 1, "box_caption": "dental-caries 0.012", "scores": {"class_score": 0.01166534423828125}, "domain": "pixel"}, {"position": {"minX": 461.0, "minY": 15.625, "maxX": 531.5, "maxY": 128.375}, "class_id": 0, "box_caption": "bone-loss 0.012", "scores": {"class_score": 0.01165771484375}, "domain": "pixel"}, {"position": {"minX": 623.0, "minY": 411.75, "maxX": 689.0, "maxY": 516.5}, "class_id": 0, "box_caption": "bone-loss 0.012", "scores": {"class_score": 0.0115966796875}, "domain": "pixel"}, {"position": {"minX": 621.0, "minY": 86.5, "maxX": 690.0, "maxY": 200.75}, "class_id": 1, "box_caption": "dental-caries 0.012", "scores": {"class_score": 0.01158905029296875}, "domain": "pixel"}, {"position": {"minX": 296.5, "minY": 354.5, "maxX": 373.5, "maxY": 452.5}, "class_id": 1, "box_caption": "dental-caries 0.012", "scores": {"class_score": 0.011566162109375}, "domain": "pixel"}, {"position": {"minX": 623.0, "minY": 447.0, "maxX": 690.0, "maxY": 546.5}, "class_id": 1, "box_caption": "dental-caries 0.012", "scores": {"class_score": 0.01154327392578125}, "domain": "pixel"}, {"position": {"minX": 299.0, "minY": 449.5, "maxX": 373.0, "maxY": 544.5}, "class_id": 1, "box_caption": "dental-caries 0.012", "scores": {"class_score": 0.01153564453125}, "domain": "pixel"}, {"position": {"minX": 529.0, "minY": 349.25, "maxX": 591.0, "maxY": 467.75}, "class_id": 1, "box_caption": "dental-caries 0.012", "scores": {"class_score": 0.01151275634765625}, "domain": "pixel"}, {"position": {"minX": 591.0, "minY": 304.0, "maxX": 656.0, "maxY": 420.5}, "class_id": 1, "box_caption": "dental-caries 0.011", "scores": {"class_score": 0.01149749755859375}, "domain": "pixel"}, {"position": {"minX": 299.0, "minY": 449.5, "maxX": 373.0, "maxY": 544.5}, "class_id": 0, "box_caption": "bone-loss 0.011", "scores": {"class_score": 0.011474609375}, "domain": "pixel"}, {"position": {"minX": 524.5, "minY": 11.0625, "maxX": 593.5, "maxY": 128.25}, "class_id": 1, "box_caption": "dental-caries 0.011", "scores": {"class_score": 0.01143646240234375}, "domain": "pixel"}, {"position": {"minX": 35.4375, "minY": 318.25, "maxX": 115.3125, "maxY": 415.25}, "class_id": 0, "box_caption": "bone-loss 0.011", "scores": {"class_score": 0.01143646240234375}, "domain": "pixel"}, {"position": {"minX": 554.5, "minY": -1.9375, "maxX": 628.5, "maxY": 99.9375}, "class_id": 1, "box_caption": "dental-caries 0.011", "scores": {"class_score": 0.01141357421875}, "domain": "pixel"}, {"position": {"minX": 559.0, "minY": 249.625, "maxX": 625.0, "maxY": 357.75}, "class_id": 1, "box_caption": "dental-caries 0.011", "scores": {"class_score": 0.01132965087890625}, "domain": "pixel"}, {"position": {"minX": 331.0, "minY": 256.5, "maxX": 403.0, "maxY": 354.0}, "class_id": 1, "box_caption": "dental-caries 0.011", "scores": {"class_score": 0.01132965087890625}, "domain": "pixel"}, {"position": {"minX": 35.4375, "minY": 318.25, "maxX": 115.3125, "maxY": 415.25}, "class_id": 1, "box_caption": "dental-caries 0.011", "scores": {"class_score": 0.011322021484375}, "domain": "pixel"}, {"position": {"minX": 559.0, "minY": 249.625, "maxX": 625.0, "maxY": 357.75}, "class_id": 0, "box_caption": "bone-loss 0.011", "scores": {"class_score": 0.0113067626953125}, "domain": "pixel"}, {"position": {"minX": 529.0, "minY": 349.25, "maxX": 591.0, "maxY": 467.75}, "class_id": 0, "box_caption": "bone-loss 0.011", "scores": {"class_score": 0.01123809814453125}, "domain": "pixel"}, {"position": {"minX": 524.5, "minY": 11.0625, "maxX": 593.5, "maxY": 128.25}, "class_id": 0, "box_caption": "bone-loss 0.011", "scores": {"class_score": 0.01116180419921875}, "domain": "pixel"}, {"position": {"minX": 331.0, "minY": 256.5, "maxX": 403.0, "maxY": 354.0}, "class_id": 0, "box_caption": "bone-loss 0.011", "scores": {"class_score": 0.01114654541015625}, "domain": "pixel"}, {"position": {"minX": 296.5, "minY": 354.5, "maxX": 373.5, "maxY": 452.5}, "class_id": 0, "box_caption": "bone-loss 0.011", "scores": {"class_score": 0.011138916015625}, "domain": "pixel"}, {"position": {"minX": 74.75, "minY": 287.25, "maxX": 151.375, "maxY": 383.75}, "class_id": 0, "box_caption": "bone-loss 0.011", "scores": {"class_score": 0.01113128662109375}, "domain": "pixel"}, {"position": {"minX": 366.75, "minY": 282.0, "maxX": 433.75, "maxY": 393.0}, "class_id": 1, "box_caption": "dental-caries 0.011", "scores": {"class_score": 0.0111236572265625}, "domain": "pixel"}, {"position": {"minX": 559.5, "minY": 347.5, "maxX": 624.5, "maxY": 461.5}, "class_id": 1, "box_caption": "dental-caries 0.011", "scores": {"class_score": 0.01110076904296875}, "domain": "pixel"}, {"position": {"minX": 492.5, "minY": 352.0, "maxX": 558.5, "maxY": 458.5}, "class_id": 1, "box_caption": "dental-caries 0.011", "scores": {"class_score": 0.01110076904296875}, "domain": "pixel"}, {"position": {"minX": 74.75, "minY": 287.25, "maxX": 151.375, "maxY": 383.75}, "class_id": 1, "box_caption": "dental-caries 0.011", "scores": {"class_score": 0.01108551025390625}, "domain": "pixel"}, {"position": {"minX": 559.5, "minY": 347.5, "maxX": 624.5, "maxY": 461.5}, "class_id": 0, "box_caption": "bone-loss 0.011", "scores": {"class_score": 0.0110626220703125}, "domain": "pixel"}, {"position": {"minX": 428.5, "minY": 351.5, "maxX": 498.5, "maxY": 464.0}, "class_id": 1, "box_caption": "dental-caries 0.011", "scores": {"class_score": 0.01105499267578125}, "domain": "pixel"}, {"position": {"minX": 8.125, "minY": 413.25, "maxX": 86.875, "maxY": 517.0}, "class_id": 1, "box_caption": "dental-caries 0.011", "scores": {"class_score": 0.01104736328125}, "domain": "pixel"}, {"position": {"minX": 624.5, "minY": 248.5, "maxX": 686.5, "maxY": 358.0}, "class_id": 0, "box_caption": "bone-loss 0.011", "scores": {"class_score": 0.01103973388671875}, "domain": "pixel"}, {"position": {"minX": 623.5, "minY": 345.5, "maxX": 688.5, "maxY": 470.5}, "class_id": 0, "box_caption": "bone-loss 0.011", "scores": {"class_score": 0.0110321044921875}, "domain": "pixel"}, {"position": {"minX": 554.5, "minY": -1.9375, "maxX": 628.5, "maxY": 99.9375}, "class_id": 0, "box_caption": "bone-loss 0.011", "scores": {"class_score": 0.011016845703125}, "domain": "pixel"}, {"position": {"minX": 591.0, "minY": 304.0, "maxX": 656.0, "maxY": 420.5}, "class_id": 0, "box_caption": "bone-loss 0.011", "scores": {"class_score": 0.010986328125}, "domain": "pixel"}, {"position": {"minX": 530.0, "minY": 307.25, "maxX": 590.0, "maxY": 418.75}, "class_id": 1, "box_caption": "dental-caries 0.011", "scores": {"class_score": 0.0109405517578125}, "domain": "pixel"}, {"position": {"minX": 428.5, "minY": 351.5, "maxX": 498.5, "maxY": 464.0}, "class_id": 0, "box_caption": "bone-loss 0.011", "scores": {"class_score": 0.0108795166015625}, "domain": "pixel"}, {"position": {"minX": 623.5, "minY": 277.75, "maxX": 688.5, "maxY": 398.25}, "class_id": 1, "box_caption": "dental-caries 0.011", "scores": {"class_score": 0.01087188720703125}, "domain": "pixel"}, {"position": {"minX": 10.4375, "minY": 316.25, "maxX": 82.8125, "maxY": 416.75}, "class_id": 0, "box_caption": "bone-loss 0.011", "scores": {"class_score": 0.01087188720703125}, "domain": "pixel"}, {"position": {"minX": 463.0, "minY": 314.25, "maxX": 531.0, "maxY": 417.25}, "class_id": 1, "box_caption": "dental-caries 0.011", "scores": {"class_score": 0.01085662841796875}, "domain": "pixel"}, {"position": {"minX": 35.78125, "minY": 449.0, "maxX": 120.125, "maxY": 543.0}, "class_id": 0, "box_caption": "bone-loss 0.011", "scores": {"class_score": 0.01085662841796875}, "domain": "pixel"}, {"position": {"minX": 492.5, "minY": 352.0, "maxX": 558.5, "maxY": 458.5}, "class_id": 0, "box_caption": "bone-loss 0.011", "scores": {"class_score": 0.0107879638671875}, "domain": "pixel"}, {"position": {"minX": 8.125, "minY": 413.25, "maxX": 86.875, "maxY": 517.0}, "class_id": 0, "box_caption": "bone-loss 0.011", "scores": {"class_score": 0.01078033447265625}, "domain": "pixel"}, {"position": {"minX": 10.4375, "minY": 316.25, "maxX": 82.8125, "maxY": 416.75}, "class_id": 1, "box_caption": "dental-caries 0.011", "scores": {"class_score": 0.01073455810546875}, "domain": "pixel"}, {"position": {"minX": 35.78125, "minY": 449.0, "maxX": 120.125, "maxY": 543.0}, "class_id": 1, "box_caption": "dental-caries 0.011", "scores": {"class_score": 0.0107269287109375}, "domain": "pixel"}, {"position": {"minX": 623.5, "minY": 363.5, "maxX": 688.5, "maxY": 489.5}, "class_id": 1, "box_caption": "dental-caries 0.011", "scores": {"class_score": 0.01071929931640625}, "domain": "pixel"}, {"position": {"minX": 530.0, "minY": 307.25, "maxX": 590.0, "maxY": 418.75}, "class_id": 0, "box_caption": "bone-loss 0.011", "scores": {"class_score": 0.01065826416015625}, "domain": "pixel"}, {"position": {"minX": 591.0, "minY": 346.75, "maxX": 656.0, "maxY": 472.25}, "class_id": 1, "box_caption": "dental-caries 0.011", "scores": {"class_score": 0.01065826416015625}, "domain": "pixel"}, {"position": {"minX": 398.25, "minY": 252.625, "maxX": 467.25, "maxY": 354.25}, "class_id": 0, "box_caption": "bone-loss 0.011", "scores": {"class_score": 0.01065826416015625}, "domain": "pixel"}, {"position": {"minX": 619.5, "minY": -1.34375, "maxX": 691.5, "maxY": 101.875}, "class_id": 1, "box_caption": "dental-caries 0.011", "scores": {"class_score": 0.0106353759765625}, "domain": "pixel"}, {"position": {"minX": 620.0, "minY": 9.71875, "maxX": 691.0, "maxY": 129.375}, "class_id": 0, "box_caption": "bone-loss 0.011", "scores": {"class_score": 0.0106048583984375}, "domain": "pixel"}, {"position": {"minX": 591.0, "minY": 346.75, "maxX": 656.0, "maxY": 472.25}, "class_id": 0, "box_caption": "bone-loss 0.011", "scores": {"class_score": 0.0106048583984375}, "domain": "pixel"}, {"position": {"minX": 620.0, "minY": 60.71875, "maxX": 690.0, "maxY": 188.375}, "class_id": 0, "box_caption": "bone-loss 0.011", "scores": {"class_score": 0.010528564453125}, "domain": "pixel"}, {"position": {"minX": 424.25, "minY": -39.28125, "maxX": 505.75, "maxY": 70.375}, "class_id": 1, "box_caption": "dental-caries 0.011", "scores": {"class_score": 0.0105133056640625}, "domain": "pixel"}, {"position": {"minX": 398.25, "minY": 252.625, "maxX": 467.25, "maxY": 354.25}, "class_id": 1, "box_caption": "dental-caries 0.011", "scores": {"class_score": 0.01050567626953125}, "domain": "pixel"}, {"position": {"minX": 366.75, "minY": 282.0, "maxX": 433.75, "maxY": 393.0}, "class_id": 0, "box_caption": "bone-loss 0.010", "scores": {"class_score": 0.01043701171875}, "domain": "pixel"}, {"position": {"minX": 459.25, "minY": -36.375, "maxX": 534.5, "maxY": 67.75}, "class_id": 1, "box_caption": "dental-caries 0.010", "scores": {"class_score": 0.01038360595703125}, "domain": "pixel"}, {"position": {"minX": 424.25, "minY": -39.28125, "maxX": 505.75, "maxY": 70.375}, "class_id": 0, "box_caption": "bone-loss 0.010", "scores": {"class_score": 0.01026153564453125}, "domain": "pixel"}, {"position": {"minX": 459.25, "minY": -36.375, "maxX": 534.5, "maxY": 67.75}, "class_id": 0, "box_caption": "bone-loss 0.010", "scores": {"class_score": 0.01013946533203125}, "domain": "pixel"}], "class_labels": {"0": "bone-loss", "1": "dental-caries"}}